{
  "type": "STANDARD",
  "hasLegacyBackendURL": false,
  "params": {
    "backendEnabled": true,
    "enableJavascriptModules": false,
    "autoStartBackend": true,
    "hideJSSecurityPanel": false,
    "envSelection": {
      "envMode": "EXPLICIT_ENV",
      "envName": "markitdown"
    },
    "nbProcesses": 1,
    "backendAPIAccessEnabled": true,
    "libraries": [
      "jquery",
      "dataiku"
    ],
    "runAs": "fabien.antoine@cgi.com",
    "infra": {
      "containerSelection": {
        "containerMode": "INHERIT"
      },
      "overrideGlobalK8sExposition": false,
      "exposition": {
        "type": "local_process",
        "params": {}
      },
      "scaling": {
        "initialReplicas": 1,
        "progressDeadlineSeconds": 600,
        "hpa": false,
        "hpaTargetCPUPercent": 0,
        "hpaMetrics": [],
        "hpaMinPods": 0,
        "hpaMaxPods": 0,
        "hpaAnnotations": []
      },
      "deploymentModifier": {
        "config": {}
      }
    },
    "forceAuthentication": false
  },
  "config": {},
  "name": "Synth-data-API",
  "apiKey": "e:AES:X2:TOv+Ga64XD4JYYEF8xix8C3DibDouoL5y4FebKJMKLi5UCBZlCIX0EqC6GO3Yfh8ir5h6VKikOtNeHWG18LXXL22XbSuWTAALXM/eNQg3KL3Y/cgQ1Xo",
  "creationTag": {
    "versionNumber": 0,
    "lastModifiedBy": {
      "login": "fabien.antoine@cgi.com"
    },
    "lastModifiedOn": 1734948333756
  },
  "tags": [],
  "checklists": {
    "checklists": []
  },
  "customFields": {},
  "isVirtual": false
}